interactive.py
main.py
utils.py
versioning.py
tools/__init__.py
tools/awscli.py
tools/az.py
tools/docker.py
tools/gcloud.py
tools/helm.py
tools/jenkins.py
tools/kubectl.py
tools/prometheus.py
tools/terraform.py
devops_cli_tools-1.0.1.dist-info/METADATA
devops_cli_tools-1.0.1.dist-info/WHEEL
devops_cli_tools-1.0.1.dist-info/entry_points.txt
devops_cli_tools-1.0.1.dist-info/top_level.txt
devops_cli_tools-1.0.1.dist-info/RECORD
